gemini_groundcite/__init__.py
gemini_groundcite/__main__.py
gemini_groundcite/cli.py
gemini_groundcite/exceptions.py
gemini_groundcite/main.py
gemini_groundcite/config/__init__.py
gemini_groundcite/config/logger.py
gemini_groundcite/config/settings.py
gemini_groundcite/core/__init__.py
gemini_groundcite/core/agents/__init__.py
gemini_groundcite/core/agents/ai_agent.py
gemini_groundcite/core/agents/clients/__init__.py
gemini_groundcite/core/agents/clients/google_gen_ai_client.py
gemini_groundcite/core/agents/clients/open_ai_client.py
gemini_groundcite/core/agents/executors/__init__.py
gemini_groundcite/core/agents/executors/citation_processor.py
gemini_groundcite/core/agents/executors/core_helper.py
gemini_groundcite/core/agents/executors/graph_executor.py
gemini_groundcite/core/agents/executors/graph_state.py
gemini_groundcite/core/agents/executors/nodes/orchestration_node.py
gemini_groundcite/core/agents/executors/nodes/parse_node.py
gemini_groundcite/core/agents/executors/nodes/search_aggregator_node.py
gemini_groundcite/core/agents/executors/nodes/search_node.py
gemini_groundcite/core/agents/executors/nodes/validation_aggregator_node.py
gemini_groundcite/core/agents/executors/nodes/validation_node.py
gemini_groundcite/core/di/__init__.py
gemini_groundcite/core/di/core_di.py
gemini_groundcite/core/models/__init__.py
gemini_groundcite/core/models/citation.py
gemini_groundcite/core/models/search_request.py
gemini_groundcite/core/utils/prompt_utils.py
gemini_groundcite-1.1.0.dist-info/licenses/LICENSE
gemini_groundcite-1.1.0.dist-info/METADATA
gemini_groundcite-1.1.0.dist-info/WHEEL
gemini_groundcite-1.1.0.dist-info/entry_points.txt
gemini_groundcite-1.1.0.dist-info/top_level.txt
gemini_groundcite-1.1.0.dist-info/RECORD
