Metadata-Version: 2.4
Name: gemini-groundcite
Version: 1.1.0
Summary: Advanced Gemini-powered search with better grounding and citation control
Author-email: Anshulee Asthana <anshulee@cennest.com>
License: MIT License
Project-URL: Homepage, https://github.com/cennest/ground-cite/tree/main/GroundCite
Project-URL: Repository, https://github.com/cennest/ground-cite.git
Project-URL: Bug Tracker, https://github.com/cennest/ground-cite/issues
Keywords: gemini,citation,grounding,analysis,nlp,statistics,ground-cite,ai
Classifier: Development Status :: 4 - Beta
Classifier: Intended Audience :: Developers
Classifier: License :: OSI Approved :: MIT License
Classifier: Programming Language :: Python :: 3
Classifier: Programming Language :: Python :: 3.12
Requires-Python: >=3.12
License-File: LICENSE
Requires-Dist: pydantic>=1.8.0
Requires-Dist: langgraph
Requires-Dist: openai
Requires-Dist: google-genai
Requires-Dist: punq>=0.7.0
Requires-Dist: click>=8.0.0
Requires-Dist: rich>=12.0.0
Provides-Extra: dev
Requires-Dist: pytest>=6.0; extra == "dev"
Requires-Dist: pytest-cov>=2.0; extra == "dev"
Requires-Dist: black>=21.0; extra == "dev"
Requires-Dist: flake8>=3.8; extra == "dev"
Requires-Dist: mypy>=0.800; extra == "dev"
Dynamic: license-file
